pdf_extractor/__init__.py
pdf_extractor/pdf_extractor.py
pdf_extractor/server.py
pdf_extraction_mcp_server-0.1.2.dist-info/METADATA
pdf_extraction_mcp_server-0.1.2.dist-info/WHEEL
pdf_extraction_mcp_server-0.1.2.dist-info/entry_points.txt
pdf_extraction_mcp_server-0.1.2.dist-info/top_level.txt
pdf_extraction_mcp_server-0.1.2.dist-info/RECORD
