Metadata-Version: 2.4
Name: pdf-extraction-mcp-server
Version: 0.1.2
Summary: Add your description here
Requires-Python: >=3.13
Requires-Dist: mcp>=1.5.0
Requires-Dist: pillow>=11.1.0
Requires-Dist: pydantic<3.0.0,>=2.10.6
Requires-Dist: pymupdf>=1.25.4
Requires-Dist: pypdf2>=3.0.1
Requires-Dist: pytesseract>=0.3.13
